examples/__init__.py
examples/client_test.py
examples/client/__init__.py
examples/client/auth_client.py
examples/client/basic_client.py
examples/client/tls_client.py
examples/cq/__init__.py
examples/cq/async.py
examples/cq/async_simple.py
examples/cq/commands.py
examples/cq/create.py
examples/cq/delete.py
examples/cq/list.py
examples/cq/queries.py
examples/pubsub/__init__.py
examples/pubsub/async.py
examples/pubsub/async_simple.py
examples/pubsub/create.py
examples/pubsub/delete.py
examples/pubsub/events.py
examples/pubsub/events_store.py
examples/pubsub/list.py
examples/pubsub/run.py
examples/queues/__init__.py
examples/queues/async.py
examples/queues/create.py
examples/queues/delete.py
examples/queues/list.py
examples/queues/queues.py
examples/queues/queues_workers.py
examples/queues/waiting_pulled.py
kubemq/__init__.py
kubemq/common/__init__.py
kubemq/common/cancellation_token.py
kubemq/common/channel_stats.py
kubemq/common/exceptions.py
kubemq/common/helpers.py
kubemq/common/requests.py
kubemq/common/subscribe_type.py
kubemq/cq/__init__.py
kubemq/cq/client.py
kubemq/cq/command_message.py
kubemq/cq/command_message_received.py
kubemq/cq/command_response_message.py
kubemq/cq/commands_subscription.py
kubemq/cq/queries_subscription.py
kubemq/cq/query_message.py
kubemq/cq/query_message_received.py
kubemq/cq/query_response_message.py
kubemq/grpc/__init__.py
kubemq/grpc/client.py
kubemq/grpc/kubemq_pb2.py
kubemq/grpc/kubemq_pb2.pyi
kubemq/grpc/kubemq_pb2_grpc.py
kubemq/pubsub/__init__.py
kubemq/pubsub/client.py
kubemq/pubsub/event_message.py
kubemq/pubsub/event_message_received.py
kubemq/pubsub/event_send_result.py
kubemq/pubsub/event_sender.py
kubemq/pubsub/event_store_message.py
kubemq/pubsub/event_store_message_received.py
kubemq/pubsub/events_store_subscription.py
kubemq/pubsub/events_subscription.py
kubemq/queues/__init__.py
kubemq/queues/client.py
kubemq/queues/downstream_receiver.py
kubemq/queues/queues_message.py
kubemq/queues/queues_message_received.py
kubemq-3.6.0.dist-info/licenses/LICENSE
kubemq-3.6.0.dist-info/METADATA
kubemq-3.6.0.dist-info/WHEEL
kubemq-3.6.0.dist-info/top_level.txt
kubemq-3.6.0.dist-info/RECORD
