Metadata-Version: 2.4
Name: kubemq
Version: 3.6.0
Summary: KubeMQ SDK for Python
Home-page: https://github.com/kubemq-io/kubemq-Python
Author: KubeMQ
Author-email: info@kubemq.io
License: MIT
Requires-Python: >=3.9
License-File: LICENSE
Requires-Dist: grpcio<2.0.0,>=1.71.0
Requires-Dist: protobuf<7.0.0,>=4.21.0
Requires-Dist: setuptools>=65.5.0
Requires-Dist: PyJWT<3.0.0,>=2.6.0
Requires-Dist: pydantic<3.0.0,>=2.0.0
Dynamic: author
Dynamic: author-email
Dynamic: description
Dynamic: description-content-type
Dynamic: home-page
Dynamic: license
Dynamic: license-file
Dynamic: requires-dist
Dynamic: requires-python
Dynamic: summary
